rsync_ssh_client/__init__.py
rsync_ssh_client/client.py
rsync_ssh_client/rsync_over_ssh.py
rsync_ssh_client-0.1.3.dist-info/licenses/LICENSE
rsync_ssh_client-0.1.3.dist-info/METADATA
rsync_ssh_client-0.1.3.dist-info/WHEEL
rsync_ssh_client-0.1.3.dist-info/entry_points.txt
rsync_ssh_client-0.1.3.dist-info/top_level.txt
rsync_ssh_client-0.1.3.dist-info/RECORD
