Metadata-Version: 2.4
Name: rsync-ssh-client
Version: 0.1.3
Summary: A Python wrapper for rsync over SSH
Author: ilia iakhin
License: Apache-2.0
Requires-Python: >=3.10
License-File: LICENSE
Requires-Dist: typer
Requires-Dist: pyyaml
Dynamic: license-file
